toodledo/__init__.py
toodledo/account.py
toodledo/authorization.py
toodledo/context.py
toodledo/custom_fields.py
toodledo/deleted_task.py
toodledo/errors.py
toodledo/folder.py
toodledo/storage.py
toodledo/task.py
toodledo/task_cache.py
toodledo/transport.py
toodledo/types.py
toodledo-1.5.1.dist-info/METADATA
toodledo-1.5.1.dist-info/WHEEL
toodledo-1.5.1.dist-info/RECORD
