Metadata-Version: 2.1
Name: toodledo
Version: 1.5.1
Summary: Python wrapper for the Toodledo v3 API which is documented at http://api.toodledo.com/3/
Home-page: https://github.com/jikamens/toodledo-python
License: MIT
Author: Jonathan Kamens
Author-email: jik@kamens.us
Requires-Python: >=3.7.2,<4.0
Classifier: Development Status :: 5 - Production/Stable
Classifier: Intended Audience :: Developers
Classifier: License :: OSI Approved :: MIT License
Classifier: Programming Language :: Python :: 3
Classifier: Programming Language :: Python :: 3.8
Classifier: Programming Language :: Python :: 3.9
Classifier: Programming Language :: Python :: 3.10
Classifier: Programming Language :: Python :: 3.11
Classifier: Programming Language :: Python :: 3.12
Classifier: Programming Language :: Python :: 3.7
Requires-Dist: marshmallow (>=3.18,<4.0)
Requires-Dist: requests (>=2.20,<3.0)
Requires-Dist: requests-oauthlib (>=1.0,<2.0)
Project-URL: changelog, https://github.com/jikamens/toodledo-python/releases
Project-URL: donate, https://www.patreon.com/jikseclecticofferings
